{"2015":{"ARIZAGA MUÑOZ JAIME SEGUNDO":120,"JARAMILLO VALAREZO CHARLES WALBERTO":71,"SERVICIO DE LIMPIEZA ULTRACLEANING G&R CIA. LTDA":89,"LANDCRYSTAL CIA. LTDA.":324,"MONTERO HINOJOSA OSCAR LEONEL":181,"ALTA SEGURIDAD PRIVADA ALPRISEG CIA LTDA":133,"RODRIGUEZ MENESES RAQUEL ANDREA":103,"AXL SA COMPAÑIA DE COMERCIO":80,"Perez Gavilanes Robinzon Humberto":114,"ADVANTLOGIC ECUADOR S.A.":266,"COMSUPPLIES S.A":390,"WANDA TECNOLOGIA CIA. LTDA.":727,"COMPUFACIL COMPUTADORAS Y FACILIDADES CIA. LTDA.":214,"LOPEZ LOPEZ EDGAR NAPOLEON":148,"CAIZA CERON MARCO ANTONIO":235,"SANCHEZ TORRES VERONICA DEL CARMEN":98,"TELLO ARTEAGA VICTOR HUGO EDGAR":80,"ARIAS DAZA RAMIRO ANIBAL":79,"TECNOPLUS CIA. LTDA.":130,"PEÑA RODAS JUAN BERNARDO":75,"HIDALGO AGUIRRE PABLO ANDRES":181,"NUÑEZ LUZURIAGA KLEVER GONZALO":217,"SANCHEZ MARTINEZ MAURO FERNANDO":72,"AKROS CIA. LTDA.":168,"becerra lituma carlos enrique":71,"GOMEZ NARANJO JHONATHAN ALEXANDER":74,"PEREIRA NARVAEZ CENEIDA MARILU":178,"ROMYKON S.A.":180,"INGEMACH S.A.":116,"CHARCO PACA JOSE ":160,"HDM ELQUITECNICA CIA. LTDA.":102,"RECOR DENTAL Y QUIMEDIC CIA. LTDA":127,"SIMED S. A.":87,"ROJAS ZAMORA JORGE ENRIQUE":71,"MALO Y ASOCIADOS MALOASO CIA. LTDA.":93,"YANEZ GARCIA YOLANDA DIOCELINA":94,"FRESENIUS KABI S.A":73,"B.BRAUN MEDICAL S.A.":99,"DISTRIBUIDORA DE MATERIALES DISMAC S.C.C.":249,"REPRESENTACIONES MEDICAS JARA FABIAN JARAFABI CIA. LTDA.":110,"BACTOBIOLOGY CIA. LTDA.":122,"SEGURIDAD Y CONFIABILIDAD C.E.S.E.P. CIA. LTDA.":75,"SEPRODA CIA. LTDA.":107,"VILLARRUEL MORA PRISCILA BRIGGITTE":85,"AUTOMET SERVICIOS AUTOMOTRICES Y METALMECANICOS CIA. LTDA.":111,"BYCACE-GROUP S.A.":102,"MAYORGA MONTENEGRO FRANKLIN EDUARDO":292,"VALDIVIESO VALDIVIESO INES REBECA":132,"VILLALOBOS VILLARREAL LILIAN PIEDAD":330,"JUAN PEÑA RODAS CIA. LTDA.":116,"IMPORTADORA LAVACOR CIA. LTDA.":95,"ZAMBONINO GUERRERO LUISA INES":98,"GRAFICAS AYERVE C. A.":216,"NICOLALDE MORENO WASHINGTON PATRICIO":249,"MUÑOZ BRAVO FREDDY ARTURO":142,"REPRESENTACIONES MOLINA HERRERA M.H. CIA. LTDA.":238,"AUSTROCOPY S.A.":131,"QUISHPE VICHISELA BLANCA MONICA":293,"VIVANCO LOPEZ INNOVATECH CIA. LTDA.":167,"ALVAREZ LARREA EQUIPOS MEDICOS ALEM CIA. LTDA.":102,"LIMERICKPHARMA CIA. LTDA.":106,"AREVALO CAÑARTE VICENTE FERNANDO":77,"IZURIETA CEVALLOS MARTHA ILIANA":119,"SILVA VITERI MARCELA BELEN":96,"PRODUCTOS ECUATORIANOS FARMACEUTICOS S.A. PRODE-FARM":106,"GUADALUPE LANDIZ ROMELIA DEL CARMEN":89,"MULTIOFICINAS CIA. LTDA.":81,"HEALTHCORP S.A.":168,"VIBAG C.A.":73,"SUMINISTROS COMERCIAL DISTRIBUCION, SUMICODI CIA. LTDA.":306,"BETANCOURT & ZAMBRANO SEGURIDAD CIA. LTDA.":80,"TONER TECNOLOGIA TONETECNOLOG CIA. LTDA.":73,"BOHORQUEZ TRIVIÑO ILDEFONSO ALBERTO":71,"CRUZ HARO CARLOS FERNANDO FELIPE":77,"RUEDA AGUILAR PATRICIA MANUELA":119,"DIAGNOSTICO SIMPLIFICADO DE PROBLEMAS EN EQUIPAMIENTO MEDICO DISPROMEDIC CIA. LTDA.":103,"Fueltala Paliacho Manuel Ernesto":109,"PRODUCTOS DE CONSTRUCCION Y FERRETERÌA PRODUFERRET S.A.":87,"Jerez Custode Marcelo Alejandro":75,"IDEAS Y GUIAS ARQUITECTONICAS IDEGUIAR CIA. LTDA.":77,"NOBOA FLORES FLORA ARACELY":115,"ORTIZ VIVAR FERNANDA SOFIA":96,"JOSE CEVALLOS JOCE CIA. LTDA.":88,"COMERCIAL URGENTONER CIA. LTDA.":82,"LOOR MOLINA FRANCISCO HERMOGENES":72,"DELGADO JARAMILLO HORACIO GIOVANNY":218,"DT MEDICAL EQUIPOS E INSUMOS MEDICOS S.A.":73,"PRODONTOMED S.A.":96,"CEVALLOS REYES GONZALO BRAULIO":97,"CERON CEVALLOS MIRIAM DE LOURDES":96,"DIAZ LOPEZ HECTOR SEGUNDO":89,"GUEVARA VERDUGA DIEGO JOHNNY":124,"ROSANIA ARISS MARIA DANIELA":76,"TORRESCAL S.A. SOLUCIONES GRAFICAS":72,"MARKETING & TECHNOLOGY MARTEC CIA. LTDA":75,"MENDIETA MUÑOZ GABRIEL FELIPE":78,"HIDROTUBCO SA":84,"CYBERBOX CIA. LTDA.":84,"CARRION ROJAS LUIS ENRIQUE":79,"ESCOBAR PORTALANZA GUSTAVO ARTURO":77,"VITERI GOMEZ MARGOTH EDITH":115,"ANDINO LEIVA DE COMERCIO S.A ALCOMERSA":75,"LLANTAS Y LOCALES SHYRIS C.A. LLANTALOCA":71,"ACRETI S.A.":82},"2016":{"TONELLO SOLUCIONES INTEGRALES CIA. LTDA.":72,"PEREIRA NARVAEZ CENEIDA MARILU":227,"JARA JARA CELIO HERIBERTO":222,"GUADALUPE LANDIZ ROMELIA DEL CARMEN":135,"VILLALOBOS VILLARREAL LILIAN PIEDAD":384,"CAIZA CERON MARCO ANTONIO":273,"LEON CHAMBA ISABEL MARIA":125,"SANCHEZ TORRES VERONICA DEL CARMEN":120,"FIRST COMPUTER SERVICE FCS S.A.":207,"CYBERBOX CIA. LTDA.":190,"WANDA TECNOLOGIA CIA. LTDA.":781,"INGEMACH S.A.":71,"GAVILANES MANZANO VICTOR HUGO":74,"ADVANTLOGIC ECUADOR S.A.":253,"VIVANCO LOPEZ INNOVATECH CIA. LTDA.":119,"ROMYKON S.A.":178,"ARIAS DAZA RAMIRO ANIBAL":115,"CHARCO PACA JOSE ":148,"EXPOSAIMEX S.A.":89,"AKROS CIA. LTDA.":134,"ALTA SEGURIDAD PRIVADA ALPRISEG CIA LTDA":180,"PINEDA PINEDA FRANCO BOLIVAR":79,"LANDCRYSTAL CIA. LTDA.":120,"CASTELO PAREDES EDGAR JAVIER":71,"ALVAREZ LARREA EQUIPOS MEDICOS ALEM CIA. LTDA.":104,"PRODUCTOS Y DISTRIBUCIONES MEDICAS ANDINO PRODIMEDA CIA. LTDA.":79,"INFORMATICA Y SISTEMAS DIGITALES DINFORSYSMEGA S.A.":90,"SIMED S. A.":91,"JUAN PEÑA RODAS CIA. LTDA.":126,"DELGADO JARAMILLO HORACIO GIOVANNY":192,"IMPORTADORA LAVACOR CIA. LTDA.":83,"SEGURIDAD Y CONFIABILIDAD C.E.S.E.P. CIA. LTDA.":92,"DISTRIBUIDORA DE MATERIALES DISMAC S.C.C.":112,"NIPRO MEDICAL CORPORATION":119,"ECUASURGICAL S.A.":94,"B.BRAUN MEDICAL S.A.":106,"VIPRISEP-VIGILANCIA PRIVADA Y SEGURIDAD PERSONAL CIA. LTDA.":83,"VITERI GOMEZ MARGOTH EDITH":95,"ALEMINSA S.A.":106,"CORREA TERAN ALEX MAURICIO":70,"AUTOMET SERVICIOS AUTOMOTRICES Y METALMECANICOS CIA. LTDA.":90,"CAJAMARCA MENDOZA MARCOS EUGENIO":75,"HDM ELQUITECNICA CIA. LTDA.":79,"ESERSUM IND. CIA. LTDA":73,"BIO-IN S.A. SISTEMAS MEDICOS":98,"IMPROHOSFAR S.A.":107,"BANDA VANONI CIA. LTDA.":75,"REPRESENTACIONES MOLINA HERRERA M.H. CIA. LTDA.":247,"MAYORGA MONTENEGRO FRANKLIN EDUARDO":115,"MAQUINARIAS Y VEHICULOS S.A. MAVESA":71,"VALDIVIESO VALDIVIESO INES REBECA":167,"IZURIETA CEVALLOS MARTHA ILIANA":182,"COMSUPPLIES S.A":255,"MUÑOZ BRAVO FREDDY ARTURO":144,"CLARATECH S.A.":76,"GENSYSTEMS S.A.":95,"Quishpe Vichisela Luis Efrain":127,"NICOLALDE MORENO WASHINGTON PATRICIO":123,"SUMINISTROS COMERCIAL DISTRIBUCION, SUMICODI CIA. LTDA.":233,"COMERCIAL URGENTONER CIA. LTDA.":100,"SANTILLAN CARGUA MIGUEL ANTONIO":69,"QUIFATEX S.A.":86,"FRESENIUS KABI S.A":94,"SANDOVAL YANEZ MARIA IMELDA":73,"LIMERICKPHARMA CIA. LTDA.":73,"REPRESENTACIONES Y COMERCIALIZADORA DE PRODUCTOS DYCOMFAR S.A.":190,"GRAFICAS AYERVE C. A.":98,"REPRESENTACIONES MEDICAS JARA FABIAN JARAFABI CIA. LTDA.":112,"GOMEZ NARANJO JHONATHAN ALEXANDER":79,"AUSTROCOPY S.A.":108,"ROSANIA ARISS MARIA DANIELA":78,"IMPORTADORA BOHORQUEZ C. LTDA.":104,"BACTOBIOLOGY CIA. LTDA.":109,"TECHCOMPUTER CIA. LTDA.":160,"FONSECA ROJAS HERNAN VINICIO":116,"LOPEZ LOPEZ EDGAR NAPOLEON":78,"VILLARRUEL MORA PRISCILA BRIGGITTE":109,"PACHECO MENA MARCIAL EFRAIN":91,"Tapia Villalba Hernán Marcelo":87,"COMPAÑÍA CONSTRUCTORA CONSDECALA CIA. LTDA.":71,"ORTEGA VILLAMAGUA WILMER AUGUSTO":71,"BORJA ESCOBAR LUIS FELIPE":81,"MORENO VALVERDE VICTOR HUGO":69,"CONSTRUCTORA VIAL CARRERA & ASOCIADOS CONVIALCAR S.A.":75,"BYCACE-GROUP S.A.":158,"ZAMBONINO GUERRERO LUISA INES":134,"JOSE CEVALLOS JOCE CIA. LTDA.":99,"MENDIETA MUÑOZ GABRIEL FELIPE":93,"RODRIGUEZ MENESES RAQUEL ANDREA":101,"RICSONS CIA. LTDA":102,"ACRETI S.A.":73,"RECOR DENTAL Y QUIMEDIC CIA. LTDA":110,"TECNOPLUS CIA. LTDA.":101,"PAZVI SEGURIDAD PAZVISEG C. LTDA.":99,"BRITO GOMEZ GUIDO ALEJANDRO":87,"PLASTILIMPIO S.A.":69,"PROTOSCANA S.A.":86,"PRODONTOMED S.A.":89,"HIDALGO AGUIRRE PABLO ANDRES":100,"Coello Valdivieso Luis Arturo":80,"Fueltala Paliacho Manuel Ernesto":158,"PAZMIÑO BORJA WILLIAM ROBERTO":73},"2017":{"TECNOPLUS CIA. LTDA.":68,"COMERCIAL URGENTONER CIA. LTDA.":144,"PLASTILIMPIO S.A.":99,"ECUASURGICAL S.A.":77,"AUSTROCOPY S.A.":94,"ARIAS DAZA RAMIRO ANIBAL":92,"GRAFICAS AYERVE C. A.":106,"CORREA TERAN ALEX MAURICIO":73,"HERNANDEZ NUÑEZ HERMEL MARCELO":70,"VILLACIS SALINAS EDWIN ANIBAL":100,"GAVILANES MANZANO VICTOR HUGO":72,"PEREZ CASTRO VICTOR HUGO":71,"RECOR DENTAL Y QUIMEDIC CIA. LTDA":126,"AKROS CIA. LTDA.":115,"MAQUINARIAS Y VEHICULOS S.A. MAVESA":95,"WANDA TECNOLOGIA CIA. LTDA.":728,"SANCHEZ PEREZ HECTOR HOMERO":67,"VINUEZA SALINAS JOHN HENRY":85,"CYBERBOX CIA. LTDA.":184,"MUÑOZ CELSO GULBERTO":69,"VILLALOBOS VILLARREAL LILIAN PIEDAD":238,"CAIZA CERON MARCO ANTONIO":347,"ROCHA SIMBAÑA CESAR PATRICIO":150,"COMSUPPLIES S.A":397,"VILLARRUEL MORA PRISCILA BRIGGITTE":146,"PEREZ PAREDES MONICA ELIZABETH":74,"MEDILABOR S.A.":84,"GUADALUPE LANDIZ ROMELIA DEL CARMEN":201,"ESPINOZA LARA JOB NOE":69,"NICOLALDE MORENO WASHINGTON PATRICIO":144,"FONSECA ROJAS HERNAN VINICIO":128,"DIAZ CAMACHO MILTON GIOVANNY":69,"JACOME PARRA EDWIN GENARO":92,"CARRION ROJAS EDGAR VICENTE":95,"ORTIZ VIVAR FERNANDA SOFIA":69,"PRODUCTOS Y DISTRIBUCIONES MEDICAS ANDINO PRODIMEDA CIA. LTDA.":103,"FERSAMAX S.A.":70,"VILLACIS CARRILLO DIEGO FRANCISCO":75,"GUAYTA GUAITA OSCAR GEOVANNY":71,"OCEHAL S.A. OBRA CIVIL, ELECTRICA, HIDRAULICA EN GENERAL":83,"HEALTHCORP S.A.":70,"TONELLO SOLUCIONES INTEGRALES CIA. LTDA.":90,"AUTOMET SERVICIOS AUTOMOTRICES Y METALMECANICOS CIA. LTDA.":68,"HDM ELQUITECNICA CIA. LTDA.":128,"JUAN PEÑA RODAS CIA. LTDA.":139,"BONJOGO S.A.":67,"CAIZA NOROÑA LUIS HERNAN":67,"GALARZA SANCHEZ EDWIN ROBINSON":91,"IRIARCO S.A.":85,"ESERSUM IND. CIA. LTDA":83,"IGLESIAS PALACIOS CARLOS GEOVANNY":77,"FALCONI LLANGARI JAVIER RAFAEL":76,"DISTRIBUIDORA DE MATERIALES DISMAC S.C.C.":146,"REPRESENTACIONES MOLINA HERRERA M.H. CIA. LTDA.":144,"VITERI GOMEZ MARGOTH EDITH":111,"DIAZ LOPEZ HECTOR SEGUNDO":131,"REPRESENTACIONES Y COMERCIALIZADORA DE PRODUCTOS DYCOMFAR S.A.":155,"PRODONTOMED S.A.":98,"SUQUILANDA TRONCOSO SANTIAGO ANTONIO":135,"LEMA CAISALITIN GONZALO":86,"GUAMINGA TACO KATHERINE YESENIA":113,"MATANGO LISINTUÑA ERICK DAVID":227,"SUMINISTROS COMERCIAL DISTRIBUCION, SUMICODI CIA. LTDA.":192,"FIRST COMPUTER SERVICE FCS S.A.":81,"ROMYKON S.A.":69,"BARRAGAN GUAMAN CAMILO AMABLE":89,"CAMPOS HERNANDEZ DANIELA NOHEMI":83,"ALEGRIA SALTOS ANA MARLENE":75,"TECHCOMPUTER CIA. LTDA.":159,"Jurado Villagómez Marco Vinicio":68,"MUÑOZ BRAVO FREDDY ARTURO":157,"PEREIRA NARVAEZ CENEIDA MARILU":106,"MENDIETA MENDEZ MARCELO RODRIGO":110,"RODRIGUEZ MENESES RAQUEL ANDREA":69,"SANCHEZ TORRES VERONICA DEL CARMEN":82,"DELGADO JARAMILLO CARLOS VINICIO":117,"SOLIS GUEVARA SILVIA JEANNETTE":220,"BIO-IN S.A. SISTEMAS MEDICOS":83,"REPRESENTACIONES MEDICAS JARA FABIAN JARAFABI CIA. LTDA.":85,"ADVANTLOGIC ECUADOR S.A.":107,"BACTOBIOLOGY CIA. LTDA.":87,"NIPRO MEDICAL CORPORATION":86,"B.BRAUN MEDICAL S.A.":68,"IZURIETA CEVALLOS MARTHA ILIANA":131,"ALVAREZ LARREA EQUIPOS MEDICOS ALEM CIA. LTDA.":79,"MAXIMAMEDICAL CIA. LTDA.":68,"IMPORTADORA LAVACOR CIA. LTDA.":91,"DISPRATTSA S.A.":67,"BYCACE-GROUP S.A.":135,"ROMERO MONTALVAN ANTONIA VANESSA":75,"AYALA CHAVEZ JOSALIN CRISTINA":71,"BRITO GOMEZ GUIDO ALEJANDRO":96,"TEXTIQUIM CIA. LTDA.":96,"COMFORTCAR S.A.":85,"VALDIVIESO VALDIVIESO INES REBECA":86,"ANDRADE PARRA JANNETH PIEDAD":86,"ZAMBONINO GUERRERO LUISA INES":106,"RUEDA AGUILAR PATRICIA MANUELA":75,"DOMINGUEZ GARZON DIANA ELIZABETH":68,"CHARCO PACA JOSE ":89,"VELEZ SUAREZ MARIA MONSERRATE":90,"JARAVITEX CIA LTDA":90,"ALTA TENSION ALTATEN S.A.":79},"2018":{"VILLACIS SALINAS EDWIN ANIBAL":105,"QUINATOA ESPIN DANILO PATRICIO":87,"Quinatoa Espín Henry Javier":76,"VARGAS VILLACIS JOHAN SEBASTIAN":84,"TIBAN JAQUE PAULINA ALEXANDRA":100,"MEDILABOR S.A.":84,"NARVAEZ TERREROS BLANCA NOEMI":86,"SUAREZ DELGADO PAOLO IVANOVICH":81,"NICOLALDE MORENO WASHINGTON PATRICIO":120,"COMSUPPLIES S.A":398,"CAMPOS HERNANDEZ DANIELA NOHEMI":115,"REPRESMUNDIAL REPRESENTACIONES INTERNACIONALES CIA. LTDA.":85,"VALDIVIESO VALDIVIESO INES REBECA":115,"IMPORTADORA LAVACOR CIA. LTDA.":131,"PEREIRA NARVAEZ CENEIDA MARILU":192,"TECNICOS EN MANTENIMIENTO Y ACCESORIOS TECMAN CIA. LTDA.":95,"CHARCO PACA JOSE ":181,"CUEVA SALAZAR MARLENE ELISABETH":88,"PEREZ PAREDES MONICA ELIZABETH":79,"FACETI S.A.":76,"ARIAS DAZA RAMIRO ANIBAL":79,"SOLIS GUEVARA SILVIA JEANNETTE":464,"VILLALOBOS VILLARREAL LILIAN PIEDAD":272,"DISPRATTSA S.A.":144,"GALARZA SANCHEZ EDWIN ROBINSON":99,"Reyes Martínez Henry Daniel":91,"RIVETUM DISEÑOS Y CONSTRUCCIONES CIA. LTDA":93,"CONSTRUCTORA MULTICONSTRUCTOR AUCANCELA MULTCONST S A":81,"QUITROPOLI CIA LTDA":118,"ANILEMA YAUTIBUG ROBERTO":110,"CAMACHO GARCIA MARLENE BEATRIZ":85,"CORREA TERAN ALEX MAURICIO":91,"GAVILANES IZURIETA MAYRA ARACELLY":87,"ALVAREZ COELLO EDWIN PATRICIO":84,"GUAYTA GUAITA OSCAR GEOVANNY":123,"CHACON ESPIN JONATAN ALEXANDER":113,"COMPAÑÍA CONSTRUCTORA CONSDECALA CIA. LTDA.":126,"ALL EQUIPMENT & SUPPLY CUENTAS EN PARTICIPACION":103,"YANEZ GARCIA YOLANDA DIOCELINA":80,"PRODUCTOS Y DISTRIBUCIONES MEDICAS ANDINO PRODIMEDA CIA. LTDA.":162,"DISTRIBUIDORA DE MATERIALES DISMAC S.C.C.":198,"QUALITYDEVELOPMENT S.A.":130,"VIERA CHASILUISA TARQUINO HUANERJES":79,"BONJOGO S.A.":98,"TONELLO SOLUCIONES INTEGRALES CIA. LTDA.":86,"QUEMCO CIA. LTDA.":95,"ALEMINSA S.A.":135,"CASTELO PAREDES EDGAR JAVIER":82,"CONSTRUCTORA OLLUMWA H&M S.A.":95,"ALTA TENSION ALTATEN S.A.":103,"ASEGURADORA DEL SUR C. A.":76,"MICROINFORMATICA MICROCOMP CIA. LTDA.":76,"ALTA SEGURIDAD PRIVADA ALPRISEG CIA LTDA":81,"ANDRADE LARA JAVIER ROBERTO":122,"IZURIETA CEVALLOS MARTHA ILIANA":150,"BRIONES MUÑIZ KARINA STEFANIA":110,"BRITO GOMEZ GUIDO ALEJANDRO":132,"REPRESENTACIONES MOLINA HERRERA M.H. CIA. LTDA.":218,"MUÑOZ BRAVO FREDDY ARTURO":168,"SUQUILANDA TRONCOSO SANTIAGO ANTONIO":112,"MATANGO LISINTUÑA ERICK DAVID":103,"DIAZ LOPEZ HECTOR SEGUNDO":85,"CARRION ROJAS EDGAR VICENTE":113,"BACTOBIOLOGY CIA. LTDA.":91,"RECOR DENTAL Y QUIMEDIC CIA. LTDA":81,"DELGADO JARAMILLO HORACIO GIOVANNY":182,"CAIZA CERON MARCO ANTONIO":149,"WANDA TECNOLOGIA CIA. LTDA.":94,"GUADALUPE LANDI RAMON LUIS":120,"TONERPLUSS S.A.":239,"MENDIETA MENDEZ MARCELO RODRIGO":132,"PACHECO BURY ALEJANDRA PAMELA":91,"SUMINISTROS COMERCIAL DISTRIBUCION, SUMICODI CIA. LTDA.":179,"ACRETI S.A.":92,"COMFORTCAR S.A.":83,"BYCACE-GROUP S.A.":172,"ZAMBONINO GUERRERO LUISA INES":126,"HDM ELQUITECNICA CIA. LTDA.":95,"UGUÑA ROSAS LUIS GERARDO":96,"Jerez Custode Marcelo Alejandro":131,"ECUASURGICAL S.A.":80,"ALVAREZ LARREA EQUIPOS MEDICOS ALEM CIA. LTDA.":121,"BIOELECTRONICA BLANCO BLANCOSA S.A.":76,"GOMEZ NARANJO JHONATHAN ALEXANDER":116,"AULESTIA FERRETERIA PUNTO COM S.A.":114,"MORALES VARAS NELSON GUILLERMO":189,"VELEZ SUAREZ MARIA MONSERRATE":364,"DISTRIBUIDORA MEINJOR IMPORT MEDIK CIA.LTDA.":99,"NIPRO MEDICAL CORPORATION":105,"B.BRAUN MEDICAL S.A.":115,"BANDA VANONI CIA. LTDA.":78,"REPRESENTACIONES MEDICAS JARA FABIAN JARAFABI CIA. LTDA.":186,"MAXIMAMEDICAL CIA. LTDA.":103,"HERNANDEZ NUÑEZ SERVICIOS Y SOLUCIONES MEDICAS CIA. LTDA.":78,"TEST LAB SUPPLIERS":100,"ANDINAMEDICAL S.A.":76,"COMERCIAL URGENTONER CIA. LTDA.":90,"ERAZO CELI GONZALO FERNANDO":78,"ERAZO AGUIRRE FREDDY GONZALO":77,"ANDRADE PARRA JANNETH PIEDAD":129,"RUEDA AGUILAR PATRICIA MANUELA":78,"DOMINGUEZ GARZON DIANA ELIZABETH":83,"REPRESENTACIONES Y COMERCIALIZADORA DE PRODUCTOS DYCOMFAR S.A.":81,"BIO-IN S.A. SISTEMAS MEDICOS":106,"CYBERBOX CIA. LTDA.":82},"2019":{"ASEGURADORA DEL SUR C. A.":169,"SEGUROS SUCRE S.A.":328,"SEGUROS ALIANZA S A":100,"GRUPO ESPECIAL DE VIGILANCIA Y SEGURIDAD GEVISE CIA. LTDA.":234,"COMPAÑIA DE CUSTODIA Y SEGURIDAD CUSTOSECURITY CIA. LTDA.":91,"DELTA SEGURIDAD PRIVADA DESEGRI CIA LTDA":168,"ALTA SEGURIDAD PRIVADA ALPRISEG CIA LTDA":284,"VIPRISEP-VIGILANCIA PRIVADA Y SEGURIDAD PERSONAL CIA. LTDA.":239,"SANCHEZ & VITERI SEGURIDAD CIA. LTDA.":371,"GONZALEZ & GONZALEZ SEGURIDAD PRIVADA SEGONPRIV CIA.LTDA.":291,"COMPAÑIA DE SEGURIDAD PRIVADA Y A PERSONAS MORESEG CIA. LTDA.":146,"JOMACH SEGURIDAD Y CUSTODIA EMPRESARIAL CIA LTDA":121,"SEGURIDAD PRIVADA DE CALIDAD SEGPRIC CIA. LTDA.":257,"FENIX SOLUCIONES INTEGRALES FENIXCON CIA.LTDA.":150,"SEGURIDAD, PROTECCIÓN Y VIGILANCIA CS5 CIA.LTDA.":189,"COSESUPA CIA. LTDA":208,"PAZVI SEGURIDAD PAZVISEG C. LTDA.":114,"SEGURPI CIA LTDA":193,"BEENGURION SECURITY CIA. LTDA.":86,"SERSEIVI SERVICIO DE SEGURIDAD Y VIGILANCIA CIA. LTDA.":97,"SEGURIDAD PRIVADA COMPAÑIA NACIONAL GUARANDA CONPAÑIANACIONALGUARANDA CIA.LTDA.":163,"DISPRATTSA S.A.":250,"QUALITYDEVELOPMENT S.A.":118,"SOLIS GUEVARA SILVIA JEANNETTE":354,"CHARCO PACA JOSE ":196,"bedoya izquierdo marcelo david":90,"B.BRAUN MEDICAL S.A.":109,"Barreno Lliguin Luis Ramiro":100,"OCEHAL S.A. OBRA CIVIL, ELECTRICA, HIDRAULICA EN GENERAL":139,"TECNICOS EN MANTENIMIENTO Y ACCESORIOS TECMAN CIA. LTDA.":139,"CYBERBOX CIA. LTDA.":88,"COMPAÑÍA CONSTRUCTORA CONSDECALA CIA. LTDA.":88,"VEINCUSTODIA CIA. LTDA.":109,"DABS7 SEGURIDAD PRIVADA CIA. LTDA.":145,"QUINCHIGUANO ÑACATO DANIEL ROBERTO":94,"CONSTRUCTORA MULTICONSTRUCTOR AUCANCELA MULTCONST S A":85,"GALARZA SANCHEZ EDWIN ROBINSON":89,"ANDRANGO ATAHUALPA WASHINGTON EFRAIN":86,"ALEMINSA S.A.":106,"GPS GLOBAL PROTECTION SECURITY GLOBALPROTECTIONSECURITY CIA. LTDA.":94,"SEVISA CIA. LTDA.":85,"DAVSEG SEGURIDAD PRIVADA CIA. LTDA.":98,"COMPAÑIA DE SEGURIDAD JARPISEG CIA. LTDA.":98,"GLOBAL ALARM SECURITY SISTEMS CIA. LTDA.":116,"SEGURIDAD Y VIGILANCIA PRIVADA SVAP CIA.LTDA.":149,"SEGURIDAD Y CONFIABILIDAD C.E.S.E.P. CIA. LTDA.":177,"SUQUILANDA TRONCOSO SANTIAGO ANTONIO":153,"PEREIRA NARVAEZ CENEIDA MARILU":136,"VILLALOBOS VILLARREAL LILIAN PIEDAD":201,"COMSUPPLIES S.A":290,"TONERPLUSS S.A.":241,"CAMPOS HERNANDEZ DANIELA NOHEMI":227,"BEDON CASTILLO VERONICA VANESSA":116,"VELEZ SUAREZ MARIA MONSERRATE":487,"BRITO GOMEZ GUIDO ALEJANDRO":171,"REPRESENTACIONES MOLINA HERRERA M.H. CIA. LTDA.":282,"BIOTECNOLOGIA Y MEDICINA BIOAMIGA CIA. LTDA.":222,"DISTRIBUIDORA MEINJOR IMPORT MEDIK CIA.LTDA.":363,"LABORATORIO VIDA (LABOVIDA) S.A.":102,"PRODUCTOS ECUATORIANOS FARMACEUTICOS S.A. PRODE-FARM":221,"MORALES VARAS NELSON GUILLERMO":298,"MUÑOZ BRAVO FREDDY ARTURO":172,"CAIZA CERON MARCO ANTONIO":94,"OLWS SEGURITY TOTAL OLWSETOTAL CIA.LTDA.":90,"AKROS CIA. LTDA.":87,"VISETRANS, VIGILANCIA, SEGURIDAD Y TRANSPORTE CIA. LTDA.":175,"RECOR DENTAL Y QUIMEDIC CIA. LTDA":88,"SUMINISTROS COMERCIAL DISTRIBUCION, SUMICODI CIA. LTDA.":140,"COMPAÑIA DE SEGURIDAD Y CONTROL SEGIRCON CIA LTDA":86,"VIBAG C.A.":91,"MEDILABOR S.A.":118,"NARVAEZ TERREROS BLANCA NOEMI":97,"ERAZO AGUIRRE FREDDY GONZALO":85,"PAPER COMPUT P-C S.A.":134,"SUAREZ DELGADO PAOLO IVANOVICH":97,"KORUMASEG CIA LTDA.":112,"RONQUILLO MURRIETA FERNANDO EDUARDO":98,"REPRESENTACIONES Y COMERCIALIZADORA DE PRODUCTOS DYCOMFAR S.A.":155,"ERAZO CELI GONZALO FERNANDO":100,"ALVAREZ LARREA EQUIPOS MEDICOS ALEM CIA. LTDA.":93,"GOMEZ NARANJO JHONATHAN ALEXANDER":88,"ANDRADE LARA JAVIER ROBERTO":147,"FRESENIUS KABI S.A":116,"HDM ELQUITECNICA CIA. LTDA.":140,"OXIALFARM CIA LTDA":103,"ACRETI S.A.":121,"MAXIMAMEDICAL CIA. LTDA.":101,"NIPRO MEDICAL CORPORATION":143,"BIO-IN S.A. SISTEMAS MEDICOS":102,"PRODUCTOS Y DISTRIBUCIONES MEDICAS ANDINO PRODIMEDA CIA. LTDA.":141,"DISTRIBUIDORA DE MATERIALES DISMAC S.C.C.":150,"REPRESENTACIONES MEDICAS JARA FABIAN JARAFABI CIA. LTDA.":101,"BACTOBIOLOGY CIA. LTDA.":100,"MEDINA MOREJON FAUSTO JAVIER":115,"DELGADO JARAMILLO HORACIO GIOVANNY":126,"SEGURIDAD PRIVADA SP4 CIA.LTDA":127,"IMPORTADORA LAVACOR CIA. LTDA.":143,"ALEMAN ROBALINO ALEXANDRA RUTH":88,"HELSINNPHARM CIA. LTDA.":162,"CARRION ROJAS EDGAR VICENTE":136,"GRANSHING SEGURIDAD CIA. LTDA.":98,"DIAZ LOPEZ HECTOR SEGUNDO":111},"2020":{"Apolo Apolo José Gonzalo":154,"VELEZ SUAREZ MARIA MONSERRATE":237,"BRITO GOMEZ GUIDO ALEJANDRO":217,"HELSINNPHARM CIA. LTDA.":185,"TEXTIQUIM CIA. LTDA.":266,"DELTA SEGURIDAD PRIVADA DESEGRI CIA LTDA":144,"ALTA SEGURIDAD PRIVADA ALPRISEG CIA LTDA":149,"VIPRISEP-VIGILANCIA PRIVADA Y SEGURIDAD PERSONAL CIA. LTDA.":174,"GONZALEZ & GONZALEZ SEGURIDAD PRIVADA SEGONPRIV CIA.LTDA.":395,"DABS7 SEGURIDAD PRIVADA CIA. LTDA.":138,"SEGUROS SUCRE S.A.":319,"DISPRATTSA S.A.":172,"SEGURIDAD PRIVADA DE CALIDAD SEGPRIC CIA. LTDA.":189,"SEGURIDAD PRIVADA COMPAÑIA NACIONAL GUARANDA CONPAÑIANACIONALGUARANDA CIA.LTDA.":420,"González Díaz Darwin Leodán":133,"BRAVO CAMPOVERDE CHRISTIAN IVAN":128,"SEGURPI CIA LTDA":152,"CONSTRUCTORA ARAGON & ARAGON CIVIL. CIA.LTDA.":121,"OLWS SEGURITY TOTAL OLWSETOTAL CIA.LTDA.":269,"ASEGURADORA DEL SUR C. A.":171,"RODAS MARQUEZ WILSON SANTIAGO":132,"MERCHAN VELEZ JAIME ENRIQUE":132,"IÑIGUEZ SANCHEZ JORGE EDUARDO":137,"ESQUIVEL GAON DAMIAN ESTEBAN":121,"ALVEAR CASTRO PABLO HERNAN":122,"BEDOYA NEIRA VINICIO EDUARDO":145,"PINTADO MATAMOROS DANNY AGUSTIN":134,"GALARZA GALINDO PAUL ESTEBAN":130,"TORRES MALDONADO JUAN FERNANDO":143,"LLIVIPUMA PULLA CESAR VICENTE":128,"ZHINDON ARGOTI ALBERTO SEGUNDO":121,"AGUILAR RAMOS JAIME RAMIRO":145,"ORELLANA QUEZADA MARCELO ESTEBAN":131,"UGUÑA ROSAS LUIS GERARDO":138,"CARDENAS IZQUIERDO MIGUEL FERNANDO":135,"PAREDES REAL WILMER ALFREDO":150,"CORDOVA ROSALES GUIDO FERNANDO":136,"MOSCOSO GUERRERO SANTIAGO LEONARDO":133,"DELEG ABRIL CRISTOBAL EDUARDO":133,"MORA ABRIL DIANA BERNARDITA":125,"CHACON CEDENO VICTOR MANUEL":138,"BARRERA TORRES DIEGO PATRICIO":121,"DOMINGUEZ VEGA ROBERTO SANTIAGO":140,"RAMIREZ REYES PABLO DANIEL":141,"TAMAYO MORA MARCELO SANTIAGO":126,"LITUMA VINTIMILLA CARLOS MANUEL":137,"JARAMILLO PAREDES GALO XAVIER":142,"MONTALVAN OLEAS JUAN CARLOS":135,"HIDALGO ALVARADO JAVIER ESTEBAN":124,"IDROVO VILLAVICENCIO JAIME WASHINGTON":130,"DELGADO BRITO GALO FABRICIO":122,"GUAYAS ULLAURI ANDRES PAULO":137,"BALAREZO GUTIERREZ RENE FERNANDO":123,"Torres López Edén José":132,"MENESES MENESES JULIO OLMEDO":128,"FALCONI LLANGARI JAVIER RAFAEL":147,"MARIN QUIZHPI ISMAEL VICENTE":132,"WILLCHES ALEMAN JUAN PABLO":126,"GUAYAS ULLAURI ANA FABIOLA":131,"MANZANO ALVARADO MARIA PAZ":122,"ZHINDON ANDRADE ALBERTO JAVIER":136,"TUAPANTE QUINTUÑA CARLOS ANDRES":130,"PEREZ DOMINGUEZ JOSE PEDRO":120,"PULLA AGUIRRE MAURO DAMIAN":124,"GUTIERREZ GARCIA WILMER GONZALO":130,"ZARATE FALCONI JUAN PABLO":124,"CORDOVA MORA JOSE DIEGO":128,"PESANTEZ ARIZAGA TELMO ESTEBAN":132,"CABRERA VALDEZ JUAN DIEGO":149,"FIGUEROA MOREJON PAUL ANDRES":151,"FLORES ESPINOZA BAYRON JAVIER":129,"ASTUDILLO AVILA VERONICA CRISTINA":128,"AVILA SOLIS JUAN PABLO":124,"TORRES RODAS MATEO XAVIER":127,"FORLAND PROJECT CIA. LTDA.":152,"EQUIPOS Y OBRAS DE INGENIERÍA OBREQUIP CÍA. LTDA.":124,"OSZY ALVARADO CONSTRUCTORA CIA.LTDA.":128,"LARIPAZ CONSTRUCTORA DEOBRASCIVILES CIA.LTDA.":129,"MATUTE PALACIOS CARLOS ANDRES":136,"PARRA MONJE VICTOR ALFREDO":133,"ACERO MONTERO JOSE REMIGIO":126,"ORELLANA AVILA PAUL ESTEBAN":126,"TORRES AGUIRRE MARCO ANTONIO":132,"VARGAS PESANTEZ FREDDY SANTIAGO":131,"SEGARRA MOLINA EDGAR ANTONIO":133,"SEGARRA NARVAEZ EDGAR FELIPE":137,"FALCONI LLANGARI DANIEL FRANCISCO":131,"GARCIA MOLINA KARLA BELEN":130,"VINTIMILLA PICON FABIAN GUSTAVO":129,"REPRESENTACIONES MOLINA HERRERA M.H. CIA. LTDA.":174,"DISTRIBUIDORA MEINJOR IMPORT MEDIK CIA.LTDA.":199,"MEJIA RIVERA CHRISTIAN VICENTE":143,"CAMPOS HERNANDEZ DANIELA NOHEMI":133,"VISETRANS, VIGILANCIA, SEGURIDAD Y TRANSPORTE CIA. LTDA.":151,"SEGURIDAD PRIVADA G2M CIA. LTDA.":148,"DELGADO JARAMILLO HORACIO GIOVANNY":123,"SOLIS GUEVARA SILVIA JEANNETTE":254,"SANCHEZ & VITERI SEGURIDAD CIA. LTDA.":182,"MEDINA MOREJON FAUSTO JAVIER":124,"TACO GOMEZ JUAN MANUEL":131},"2021":{"OLWS SEGURITY TOTAL OLWSETOTAL CIA.LTDA.":176,"SEGURIDAD PRIVADA COMPAÑIA NACIONAL GUARANDA CONPAÑIANACIONALGUARANDA CIA.LTDA.":693,"VISETRANS, VIGILANCIA, SEGURIDAD Y TRANSPORTE CIA. LTDA.":136,"CONSTRUCTORA VIAL CONSCONASIM CIA. LTDA.":92,"Barreno Lliguin Luis Ramiro":131,"L&M DE SEGURIDAD PRIVADA CIA LTDA":90,"GONZALEZ & GONZALEZ SEGURIDAD PRIVADA SEGONPRIV CIA.LTDA.":271,"ALTA SEGURIDAD PRIVADA ALPRISEG CIA LTDA":133,"SEGUROS SUCRE S.A.":109,"ASEGURADORA DEL SUR C. A.":134,"SEGUROS ALIANZA S A":118,"LARREA NARVAEZ FERNANDO RAMIRO":93,"CONSTRUCCIONES ROLANDO CUAMACAS VEGA VEGACUCONSTRUCCIONES CIA.LTDA.":100,"PEREZ RODRIGUEZ CHRISTIAN ALEJANDRO":86,"SEGURPI CIA LTDA":184,"SISTEMAS Y SERVICIOS DE VIGILANCIA PRIVADA SYSVA CIA. LTDA":164,"WOLF FORCE SECURITY WFS C.L.":164,"DELTA SEGURIDAD PRIVADA DESEGRI CIA LTDA":131,"COSESUPA CIA. LTDA":130,"VIPRISEP-VIGILANCIA PRIVADA Y SEGURIDAD PERSONAL CIA. LTDA.":171,"SEGCOMPRI CIA. LTDA.":105,"DABS7 SEGURIDAD PRIVADA CIA. LTDA.":149,"SEGURIDAD Y CONFIABILIDAD C.E.S.E.P. CIA. LTDA.":128,"PROTECCION Y SEGURIDAD F&BPROSEG CIA.LTDA.":99,"CASEMAGER COMPAÑIA DE SEGURIDAD MARIA GERARDA CIA. LTDA.":88,"PRODUCTOS Y DISTRIBUCIONES MEDICAS ANDINO PRODIMEDA CIA. LTDA.":132,"TEXTIQUIM CIA. LTDA.":403,"PROTECCION ARMADA Y TECNOLOGICA ARMYPROTEC CIA.LTDA.":109,"GLOBAL ALARM SECURITY SISTEMS CIA. LTDA.":105,"MAX.SECURITY CIA LTDA":112,"SERVICIOS PROFESIONALES DE PROTECCION SIPROC CIA.LTDA.":139,"KORUMASEG CIA LTDA.":158,"SEGURIDAD PRIVADA G2M CIA. LTDA.":105,"SEGURIDAD, PROTECCIÓN Y VIGILANCIA CS5 CIA.LTDA.":258,"LABORATORIO VIDA (LABOVIDA) S.A.":115,"PRODUCTOS ECUATORIANOS FARMACEUTICOS S.A. PRODE-FARM":112,"REPRESENTACIONES Y COMERCIALIZADORA DE PRODUCTOS DYCOMFAR S.A.":117,"SEGURIDAD PRIVADA DE CALIDAD SEGPRIC CIA. LTDA.":158,"DELGADO JARAMILLO HORACIO GIOVANNY":224,"HERRERA CELA RODRIGO XAVIER":116,"REPRESENTACIONES MEDICAS JARA FABIAN JARAFABI CIA. LTDA.":92,"GRUPO ESPECIAL DE VIGILANCIA Y SEGURIDAD GEVISE CIA. LTDA.":156,"COMPAÑIA DE SEGURIDAD Y CONTROL SEGIRCON CIA LTDA":99,"FENIX SOLUCIONES INTEGRALES FENIXCON CIA.LTDA.":118,"SANCHEZ & VITERI SEGURIDAD CIA. LTDA.":249,"WORKINGSEGURITY CIA.LTDA.":95,"BACTOBIOLOGY CIA. LTDA.":91,"SOLIS GUEVARA SILVIA JEANNETTE":156,"FRESENIUS KABI S.A":104,"CHARCO PACA JOSE ":141,"DISTRIBUIDORA DE MEDICAMENTOS DISPRESFARMA CIA. LTDA.":107,"DISTRIBUIDORA MEINJOR IMPORT MEDIK CIA.LTDA.":186,"SERVICIO DE LIMPIEZA ULTRACLEANING G&R CIA. LTDA":98,"DISPRATTSA S.A.":141,"SEGURIDAD Y VIGILANCIA PRIVADA SVAP CIA.LTDA.":98,"AGENTES DE SEGURIDAD Y VIGILANCIA AGENTESEG CIA.LTDA.":112,"RACINES VIZUETE DARWIN EDUARDO":85,"OCHOA CHICAIZA SILVANA MARGOTH":85,"PROTECCION INTEGRAL PROTINGRAL CIA LTDA":124,"REPRESENTACIONES MOLINA HERRERA M.H. CIA. LTDA.":211,"CAMPOS HERNANDEZ DANIELA NOHEMI":96,"VILLALOBOS VILLARREAL LILIAN PIEDAD":87,"COMSUPPLIES S.A":85,"Apolo Apolo José Gonzalo":121,"Loza Vega Luis Luis":93,"ANDRANGO ATAHUALPA WASHINGTON EFRAIN":97,"SHUGULI GUACOLLANTE HECTOR RODRIGO":88,"NIPRO MEDICAL CORPORATION":111,"NARVAEZ TERREROS BLANCA NOEMI":123,"RONQUILLO MURRIETA FERNANDO EDUARDO":121,"GYKORMED S.A.":204,"MEDIVITALSCC S.A.":124,"MUÑOZ BAJAÑA NARCISA DEL CARMEN":108,"MEDIKACARE CIA.LTDA.":138,"BARRIGA RUIZ ROMMEL ROLANDO":101,"BERNI PINTO ALVARO CLEMENTE":93,"FERNANDEZ PAUCAR LUIS OLMEDO":101,"AGUIRRE TOBAR DIEGO JAVIER":108,"DAVSEG SEGURIDAD PRIVADA CIA. LTDA.":99,"VIDAPROTEC CIA LTDA":200,"BIOTECNOLOGIA Y MEDICINA BIOAMIGA CIA. LTDA.":95,"MV IMPORTACIONES MV-IMP CIA. LTDA.":85,"COMPAÑIA DE SEGURIDAD PRIVADA Y A PERSONAS MORESEG CIA. LTDA.":153,"MOROCHO CATAGNIA FREDDY ALEJANDRO":109,"COOPERATIVA DE MAESTROS ESPECIALIZADOS EN LA CONSTRUCCION CIVIL Y ANEXOS COOPECC":88,"FLORES RIVERA AUGUSTO GABRIEL":86,"AGUILAR MOROCHO ERICK ALEJANDRO":100,"PIEDRA CONSTANTE TELMO GONZALO":102,"TACO GOMEZ JUAN MANUEL":89,"CHICAIZA ULLE MANUEL FERNANDO":124,"SANDOVAL PALLO JORGE GERMAN":96,"KD CONSTRUCCIONES KEDACONSTRU CIA.LTDA.":92,"MEJIA RIVERA CHRISTIAN VICENTE":255,"VARTRAXHEALTH S.A.":195,"GONARMI SEGURIDAD PRIVADA CIA.LTDA.":122,"SEGURITYRIVAS CIA.LTDA.":120,"MORALES VARAS NELSON GUILLERMO":146,"SOULPHARMA CIA LTDA":92,"SEGURIDAD TECNICA DE IWIAS IWSEL CIA. LTDA.":96,"BRITO GOMEZ GUIDO ALEJANDRO":201},"2022":{"LOACHAMIN CHANO FREDDY DANIEL":77,"SOULPHARMA CIA LTDA":82,"LABORATORIO VIDA (LABOVIDA) S.A.":79,"Brito Gomez Guido Alejandro":90,"MEJIA RIVERA CHRISTIAN VICENTE":198,"REPRESENTACIONES MOLINA HERRERA M.H. CIA. LTDA.":148,"DISTRIBUIDORA MEINJOR IMPORT MEDIK CIA.LTDA.":93,"GYKORMED S.A.":129,"PRODUCTOS Y DISTRIBUCIONES MEDICAS ANDINO PRODIMEDA CIA. LTDA.":93,"MEDIVITALSCC S.A.":74,"DAVSEG SEGURIDAD PRIVADA CIA. LTDA.":83,"DABS7 SEGURIDAD PRIVADA CIA. LTDA.":79,"SEGURIDAD Y CONFIABILIDAD C.E.S.E.P. CIA. LTDA.":78,"SEGURIDAD PRIVADA COMPAÑIA NACIONAL GUARANDA CONPAÑIANACIONALGUARANDA CIA.LTDA.":348,"SEGURIDAD, PROTECCIÓN Y VIGILANCIA CS5 CIA.LTDA.":258,"PROTECCION INTEGRAL PROTINGRAL CIA LTDA":69,"SEGURIDAD PRIVADA G2M CIA. LTDA.":80,"KORUMASEG CIA LTDA.":162,"DELGADO JARAMILLO HORACIO GIOVANNY":115,"SOLIS GUEVARA SILVIA JEANNETTE":124,"SEGURIDAD PRIVADA DE CALIDAD SEGPRIC CIA. LTDA.":79,"VIPRISEP-VIGILANCIA PRIVADA Y SEGURIDAD PERSONAL CIA. LTDA.":75,"VISETRANS, VIGILANCIA, SEGURIDAD Y TRANSPORTE CIA. LTDA.":79,"GONZALEZ & GONZALEZ SEGURIDAD PRIVADA SEGONPRIV CIA.LTDA.":194,"WOLF FORCE SECURITY WFS C.L.":129,"TEXTIQUIM CIA. LTDA.":175,"DISPRATTSA S.A.":90,"SEGURITYRIVAS CIA.LTDA.":72,"VARTRAXHEALTH S.A.":80,"RONQUILLO MURRIETA FERNANDO EDUARDO":80,"SANCHEZ & VITERI SEGURIDAD CIA. LTDA.":86,"BEDOYA NEIRA VINICIO EDUARDO":80,"LEON ALVARADO JUAN PABLO":79,"JIMBO QUIZHPE FREDY MAURICIO":78,"UGUÑA ROSAS LUIS GERARDO":81,"MOYANO MACHADO GEOVANNI FERNANDO":71,"CALLE AREVALO JORGE LUIS":69,"IÑIGUEZ SANCHEZ JORGE EDUARDO":82,"JARAMILLO VINTIMILLA XAVIER NAPOLEON":76,"PACHECO MORENO ESTEBAN MAURICIO":71,"IDROVO VILLAVICENCIO JAIME WASHINGTON":69,"GUAYAS ULLAURI ANDRES PAULO":73,"RAMIREZ REYES PABLO DANIEL":78,"COELLO PALACIOS JAIME ROBERTO":70,"AGUILAR RAMOS JAIME RAMIRO":70,"RAMIREZ ROJAS CRISTIAN ADRIAN":69,"LOPEZ MERCHAN HERMEL RODRIGO":72,"MONTALVAN OLEAS JUAN CARLOS":78,"FORLAND PROJECT CIA. LTDA.":77,"MENESES MENESES JULIO OLMEDO":76,"GUAYAS ULLAURI ANA FABIOLA":71,"LARRIVA RODRIGUEZ VALERIA BEATRIZ":79,"CABRERA VALDEZ JUAN DIEGO":80,"GARCIA GARCIA DIEGO GUSTAVO":84,"OYERVIDE SOTO ESTEBAN MAURICIO":72,"PIEDRA VARGAS BYRON PATRICIO":71,"AVILA LAZO XIMENA MICAELA":72,"Andrade Carchi Paola Valeria":69,"ALVARADO ZENTENO DAVID EMMANUEL":69,"SANCHEZ ORDOÑEZ SAMUEL ESTEBAN":71,"ASTUDILLO LIMA MARCELO ANDRES":75,"LEON JARAMILLO ADRIANA ALEJANDRA":71,"AGUILAR TENEMAZA DANIEL ALEJANDRO":84,"QUEZADA SANCHEZ BYRON XAVIER":71,"ESQUIVEL GAON DAMIAN ESTEBAN":71,"VARGAS PESANTEZ FREDDY SANTIAGO":70,"AGUIRRE RIVADENEIRA HERNAN XAVIER":77,"VALDIVIESO TORRES FABRICIO ANTONIO":83,"LLIVIPUMA PULLA CESAR VICENTE":72,"REA ORELLANA WILLIAM FERNANDO":71,"MARIN QUIZHPI ISMAEL VICENTE":83,"OSZY ALVARADO CONSTRUCTORA CIA.LTDA.":81,"GUAMAN MENDOZA DANIEL EDUARDO":69,"COBOS GALINDO MARCO ANTONIO":72,"TORRES MALDONADO JUAN FERNANDO":74,"RODAS ORDOÑEZ PABLO ARTURO":69,"FIGUEROA MOREJON PAUL ANDRES":75,"CAJAMARCA MARTINEZ EDISSON GEOVANNY":80,"LOPEZ MERCHAN PEDRO DAVID":74,"JARAMILLO PAREDES GALO XAVIER":89,"GUTIERREZ GARCIA WILMER GONZALO":71,"BALAREZO GUTIERREZ RENE FERNANDO":72,"MALDONADO NOBOA CESAR HUMBERTO":71,"MERCHAN VELEZ JAIME ENRIQUE":70,"MALDONADO NOBOA JUAN SEBASTIAN":69,"NUÑEZ AVILA BOLIVAR ANDRES":69,"RAMOS RAMOS FAUSTO ROBERTO":70,"VINTIMILLA PICON FABIAN GUSTAVO":84,"PARRA MONJE VICTOR ALFREDO":71,"TORRES RODAS MATEO XAVIER":71,"ORCONSTRUCIVEL S.A.S.":78,"MAX.SECURITY CIA LTDA":144,"COSESUPA CIA. LTDA":75,"SISTEMAS Y SERVICIOS DE VIGILANCIA PRIVADA SYSVA CIA. LTDA":94,"GONARMI SEGURIDAD PRIVADA CIA.LTDA.":88,"SEGURIDAD TECNICA DE IWIAS IWSEL CIA. LTDA.":97,"ALTA SEGURIDAD PRIVADA ALPRISEG CIA LTDA":83,"LARREA NARVAEZ FERNANDO RAMIRO":69,"HENRY DANIEL REYES MARTINEZ CONSTRUCTORA EQUIREDCONSTRUCCIONES S.A.":69,"KD CONSTRUCCIONES KEDACONSTRU CIA.LTDA.":72,"Barreno Lliguin Luis Ramiro":80,"FERNANDEZ PAUCAR LUIS OLMEDO":70,"PIZZELI TEXTILES PIZZELITEX S.A.":87,"CHICAIZA ULLE MANUEL FERNANDO":87,"FRANCOSEGURIDAD CIA.LTDA.":81,"Loza Vega Luis Ernesto":69,"GLOBAL ALARM SECURITY SISTEMS CIA. LTDA.":71,"OLWS SEGURITY TOTAL OLWSETOTAL CIA.LTDA.":76,"SEGURPI CIA LTDA":82}}
